indico_price_adjustments/__init__.py
indico_price_adjustments/plugin.py
indico_price_adjustments/migrations/20250902_1626_0f39ab4cda69_add_column_extra_fee_for_guests.py
indico_price_adjustments-1.0.0.dist-info/METADATA
indico_price_adjustments-1.0.0.dist-info/WHEEL
indico_price_adjustments-1.0.0.dist-info/entry_points.txt
indico_price_adjustments-1.0.0.dist-info/licenses/LICENSE
indico_price_adjustments-1.0.0.dist-info/RECORD
