Metadata-Version: 2.4
Name: indico-price-adjustments
Version: 1.0.0
Summary: Price adjustments for logged in users
Project-URL: GitHub, https://github.com/RobotHanzo/IndicoPriceAdjustments
Author-email: RobotHanzo <admin@robothanzo.dev>
License: MIT License
License-File: LICENSE
Classifier: Environment :: Plugins
Classifier: Environment :: Web Environment
Classifier: Programming Language :: Python :: 3.12
Requires-Python: <3.13,>=3.12
Requires-Dist: indico-patcher>=0.2.1
Requires-Dist: indico>=3.3
Requires-Dist: pygments<3,>=2.7.2
